phenopy/__init__.py
phenopy/__main__.py
phenopy/build_hpo.py
phenopy/config.py
phenopy/d2p.py
phenopy/data/lgb.model.pkl
phenopy/data/oa_phenotype_age.tsv
phenopy/data/phenopy.wv.model.txt.gz
phenopy/data/phenotype_groups.txt
phenopy/ic.py
phenopy/network.py
phenopy/score.py
phenopy/util.py
phenopy/weights.py
phenopy-0.6.0.dist-info/LICENSE
phenopy-0.6.0.dist-info/METADATA
phenopy-0.6.0.dist-info/WHEEL
phenopy-0.6.0.dist-info/entry_points.txt
phenopy-0.6.0.dist-info/RECORD
