Metadata-Version: 2.1
Name: phenopy
Version: 0.6.0
Summary: Phenotype comparison scoring by semantic similarity.
Author: Kevin Arvai
Requires-Python: >=3.9,<4.0
Classifier: Programming Language :: Python :: 3
Classifier: Programming Language :: Python :: 3.9
Classifier: Programming Language :: Python :: 3.10
Classifier: Programming Language :: Python :: 3.11
Requires-Dist: fire (>=0.5.0,<0.6.0)
Requires-Dist: gensim (>=4.3.0,<5.0.0)
Requires-Dist: networkx (==2.6.3)
Requires-Dist: numpy (>=1.21.1,<2.0.0)
Requires-Dist: obonet (>=1.0.0,<2.0.0)
Requires-Dist: pandas (>=1.0.0,<2.0.0)
Requires-Dist: pytest (>=7.3.1,<8.0.0)
Requires-Dist: requests (>=2.31.0,<3.0.0)
Requires-Dist: scipy (>=1.6.1,<2.0.0)
Project-URL: Bug Tracker, https://github.com/GeneDx/phenopy/issues
Project-URL: homepage, https://github.com/GeneDx/phenopy
